hdmf_zarr/__init__.py
hdmf_zarr/_due.py
hdmf_zarr/_version.py
hdmf_zarr/backend.py
hdmf_zarr/nwb.py
hdmf_zarr/utils.py
hdmf_zarr/zarr_utils.py
hdmf_zarr-0.12.0.dist-info/METADATA
hdmf_zarr-0.12.0.dist-info/WHEEL
hdmf_zarr-0.12.0.dist-info/licenses/LICENSE.txt
hdmf_zarr-0.12.0.dist-info/RECORD
