Metadata-Version: 2.4
Name: hdmf_zarr
Version: 0.12.0
Summary: A package defining a Zarr I/O backend for HDMF
Project-URL: Homepage, https://github.com/hdmf-dev/hdmf-zarr
Project-URL: Bug Tracker, https://github.com/hdmf-dev/hdmf-zarr/issues
Author-email: Oliver Ruebel <oruebel@lbl.gov>, Matthew Avaylon <mavaylon@lbl.gov>, Ryan Ly <rly@lbl.gov>, Stephanie Prince <smprince@lbl.gov>
License: BSD
License-File: LICENSE.txt
Classifier: Development Status :: 4 - Beta
Classifier: Intended Audience :: Developers
Classifier: Intended Audience :: Science/Research
Classifier: License :: OSI Approved :: BSD License
Classifier: Operating System :: MacOS
Classifier: Operating System :: Microsoft :: Windows
Classifier: Operating System :: Unix
Classifier: Programming Language :: Python
Classifier: Programming Language :: Python :: 3.9
Classifier: Programming Language :: Python :: 3.10
Classifier: Programming Language :: Python :: 3.11
Classifier: Programming Language :: Python :: 3.12
Classifier: Programming Language :: Python :: 3.13
Classifier: Topic :: Scientific/Engineering :: Medical Science Apps.
Requires-Python: >=3.9
Requires-Dist: hdmf>=4.1.0
Requires-Dist: numcodecs<0.16.0,>=0.12.0
Requires-Dist: numpy>=1.24.0
Requires-Dist: pynwb>=2.8.3
Requires-Dist: threadpoolctl>=3.1.0
Requires-Dist: zarr<3.0,>=2.18.0
Provides-Extra: all
Requires-Dist: black; extra == 'all'
Requires-Dist: codespell; extra == 'all'
Requires-Dist: fsspec; extra == 'all'
Requires-Dist: hdf5plugin; extra == 'all'
Requires-Dist: matplotlib; extra == 'all'
Requires-Dist: pre-commit; extra == 'all'
Requires-Dist: pytest; extra == 'all'
Requires-Dist: pytest-cov; extra == 'all'
Requires-Dist: python-dateutil; extra == 'all'
Requires-Dist: ruff; extra == 'all'
Requires-Dist: s3fs; extra == 'all'
Requires-Dist: scipy; extra == 'all'
Requires-Dist: sphinx-copybutton; extra == 'all'
Requires-Dist: sphinx-gallery; extra == 'all'
Requires-Dist: sphinx-rtd-theme>=1; extra == 'all'
Requires-Dist: sphinx>=4; extra == 'all'
Requires-Dist: tox; extra == 'all'
Requires-Dist: tqdm>=4.41.0; extra == 'all'
Provides-Extra: docs
Requires-Dist: matplotlib; extra == 'docs'
Requires-Dist: scipy; extra == 'docs'
Requires-Dist: sphinx-copybutton; extra == 'docs'
Requires-Dist: sphinx-gallery; extra == 'docs'
Requires-Dist: sphinx-rtd-theme>=1; extra == 'docs'
Requires-Dist: sphinx>=4; extra == 'docs'
Provides-Extra: full
Requires-Dist: fsspec; extra == 'full'
Requires-Dist: s3fs; extra == 'full'
Requires-Dist: tqdm>=4.41.0; extra == 'full'
Provides-Extra: test
Requires-Dist: black; extra == 'test'
Requires-Dist: codespell; extra == 'test'
Requires-Dist: hdf5plugin; extra == 'test'
Requires-Dist: pre-commit; extra == 'test'
Requires-Dist: pytest; extra == 'test'
Requires-Dist: pytest-cov; extra == 'test'
Requires-Dist: python-dateutil; extra == 'test'
Requires-Dist: ruff; extra == 'test'
Requires-Dist: scipy; extra == 'test'
Requires-Dist: tox; extra == 'test'
